idnumbers/__init__.py
idnumbers/nationalid/ALB.py
idnumbers/nationalid/ARE.py
idnumbers/nationalid/ARG.py
idnumbers/nationalid/AUS.py
idnumbers/nationalid/AUT.py
idnumbers/nationalid/BEL.py
idnumbers/nationalid/BGD.py
idnumbers/nationalid/BGR.py
idnumbers/nationalid/BHR.py
idnumbers/nationalid/BIH.py
idnumbers/nationalid/BRA.py
idnumbers/nationalid/CAN.py
idnumbers/nationalid/CHE.py
idnumbers/nationalid/CHL.py
idnumbers/nationalid/CHN.py
idnumbers/nationalid/COL.py
idnumbers/nationalid/CZE.py
idnumbers/nationalid/DEU.py
idnumbers/nationalid/DNK.py
idnumbers/nationalid/ESP.py
idnumbers/nationalid/EST.py
idnumbers/nationalid/FIN.py
idnumbers/nationalid/FRA.py
idnumbers/nationalid/GBR.py
idnumbers/nationalid/GEO.py
idnumbers/nationalid/GRC.py
idnumbers/nationalid/HKG.py
idnumbers/nationalid/HRV.py
idnumbers/nationalid/HUN.py
idnumbers/nationalid/IDN.py
idnumbers/nationalid/IND.py
idnumbers/nationalid/IRL.py
idnumbers/nationalid/IRN.py
idnumbers/nationalid/IRQ.py
idnumbers/nationalid/ISL.py
idnumbers/nationalid/ISR.py
idnumbers/nationalid/ITA.py
idnumbers/nationalid/JPN.py
idnumbers/nationalid/KAZ.py
idnumbers/nationalid/KOR.py
idnumbers/nationalid/KWT.py
idnumbers/nationalid/LKA.py
idnumbers/nationalid/LTU.py
idnumbers/nationalid/LUX.py
idnumbers/nationalid/LVA.py
idnumbers/nationalid/MAC.py
idnumbers/nationalid/MDA.py
idnumbers/nationalid/MEX.py
idnumbers/nationalid/MKD.py
idnumbers/nationalid/MNE.py
idnumbers/nationalid/MYS.py
idnumbers/nationalid/NGA.py
idnumbers/nationalid/NLD.py
idnumbers/nationalid/NOR.py
idnumbers/nationalid/NPL.py
idnumbers/nationalid/NZL.py
idnumbers/nationalid/PAK.py
idnumbers/nationalid/PHL.py
idnumbers/nationalid/PNG.py
idnumbers/nationalid/POL.py
idnumbers/nationalid/PRT.py
idnumbers/nationalid/ROU.py
idnumbers/nationalid/SGP.py
idnumbers/nationalid/SMR.py
idnumbers/nationalid/SRB.py
idnumbers/nationalid/SVK.py
idnumbers/nationalid/SVN.py
idnumbers/nationalid/SWE.py
idnumbers/nationalid/THA.py
idnumbers/nationalid/TUR.py
idnumbers-1.11.0.dist-info/LICENSE
idnumbers-1.11.0.dist-info/METADATA
idnumbers-1.11.0.dist-info/WHEEL
idnumbers-1.11.0.dist-info/top_level.txt
idnumbers-1.11.0.dist-info/RECORD
