Metadata-Version: 2.1
Name: idnumbers
Version: 1.11.0
Summary: id numbers verification toolkits
Home-page: https://github.com/Identique/idnumbers
Author: Identique
Author-email: microdataxyz@outlook.com
License: MIT
Project-URL: Source, https://github.com/Identique/idnumbers
Project-URL: Tracker, https://github.com/Identique/idnumbers/issues
Classifier: Development Status :: 5 - Production/Stable
Classifier: Intended Audience :: Developers
Classifier: License :: OSI Approved :: MIT License
Classifier: Operating System :: OS Independent
Classifier: Programming Language :: Python :: 3.9
Classifier: Programming Language :: Python :: 3.10
Classifier: Programming Language :: Python :: 3.11
Classifier: Programming Language :: Python :: 3.12
Classifier: Topic :: Software Development :: Libraries :: Python Modules
Classifier: Topic :: Utilities
Classifier: Typing :: Typed
Requires-Python: >=3.9
License-File: LICENSE
